Workbook

Sheet Cómo usar
A1: Losetas Chile · ventas y comisión
A3: 1. Registra una venta por fila en la hoja Ventas. | B3: El monto de productos debe ser el valor final cobrado por productos, después de descuentos y sin envío.
A4: 2. Anota el envío aparte. | B4: El total del cliente suma productos + envío; la comisión usa únicamente el monto de productos.
A5: 3. Marca el estado Vendida. | B5: La comisión se calcula solo para ventas marcadas Vendida. Pendiente, Cancelada y Devuelta no generan comisión.
A6: 4. Registra lo que ya te pagaron. | B6: La columna Comisión pagada descuenta abonos de tu saldo pendiente.
A7: 5. Completa Productos cuando tengas la lista. | B7: Esta hoja sirve para ordenar el catálogo y después cargar los precios correctos al dashboard de ZERO.
A8: 6. Ajusta el porcentaje si alguna vez cambia. | B8: La tasa está en Resumen!B3 y comienza en 10%.

Sheet Ventas
A1: Registro de ventas · Losetas Chile
A2: Celdas amarillas: ingresar datos. Celdas grises: cálculo automático. Una fila por venta.
A3: Fecha | B3: Pedido / folio | C3: Cliente | D3: Producto(s) / detalle | E3: Productos cobrados | F3: Envío cobrado | G3: Total cliente | H3: Estado | I3: Comisión 10% | J3: Comisión pagada | K3: Saldo pendiente | L3: Observaciones
G4: =IF(E4="","",E4+IF(F4="",0,F4)) | I4: =IF(E4="","",IF(H4="Vendida",E4*Resumen!$B$3,0)) | K4: =IF(I4="","",MAX(0,I4-IF(J4="",0,J4)))
G5: =IF(E5="","",E5+IF(F5="",0,F5)) | I5: =IF(E5="","",IF(H5="Vendida",E5*Resumen!$B$3,0)) | K5: =IF(I5="","",MAX(0,I5-IF(J5="",0,J5)))
G6: =IF(E6="","",E6+IF(F6="",0,F6)) | I6: =IF(E6="","",IF(H6="Vendida",E6*Resumen!$B$3,0)) | K6: =IF(I6="","",MAX(0,I6-IF(J6="",0,J6)))
G7: =IF(E7="","",E7+IF(F7="",0,F7)) | I7: =IF(E7="","",IF(H7="Vendida",E7*Resumen!$B$3,0)) | K7: =IF(I7="","",MAX(0,I7-IF(J7="",0,J7)))
G8: =IF(E8="","",E8+IF(F8="",0,F8)) | I8: =IF(E8="","",IF(H8="Vendida",E8*Resumen!$B$3,0)) | K8: =IF(I8="","",MAX(0,I8-IF(J8="",0,J8)))
G9: =IF(E9="","",E9+IF(F9="",0,F9)) | I9: =IF(E9="","",IF(H9="Vendida",E9*Resumen!$B$3,0)) | K9: =IF(I9="","",MAX(0,I9-IF(J9="",0,J9)))
G10: =IF(E10="","",E10+IF(F10="",0,F10)) | I10: =IF(E10="","",IF(H10="Vendida",E10*Resumen!$B$3,0)) | K10: =IF(I10="","",MAX(0,I10-IF(J10="",0,J10)))
G11: =IF(E11="","",E11+IF(F11="",0,F11)) | I11: =IF(E11="","",IF(H11="Vendida",E11*Resumen!$B$3,0)) | K11: =IF(I11="","",MAX(0,I11-IF(J11="",0,J11)))
G12: =IF(E12="","",E12+IF(F12="",0,F12)) | I12: =IF(E12="","",IF(H12="Vendida",E12*Resumen!$B$3,0)) | K12: =IF(I12="","",MAX(0,I12-IF(J12="",0,J12)))
G13: =IF(E13="","",E13+IF(F13="",0,F13)) | I13: =IF(E13="","",IF(H13="Vendida",E13*Resumen!$B$3,0)) | K13: =IF(I13="","",MAX(0,I13-IF(J13="",0,J13)))
G14: =IF(E14="","",E14+IF(F14="",0,F14)) | I14: =IF(E14="","",IF(H14="Vendida",E14*Resumen!$B$3,0)) | K14: =IF(I14="","",MAX(0,I14-IF(J14="",0,J14)))
G15: =IF(E15="","",E15+IF(F15="",0,F15)) | I15: =IF(E15="","",IF(H15="Vendida",E15*Resumen!$B$3,0)) | K15: =IF(I15="","",MAX(0,I15-IF(J15="",0,J15)))
... G503: =IF(E503="","",E503+IF(F503="",0,F503)) | I503: =IF(E503="","",IF(H503="Vendida",E503*Resumen!$B$3,0)) | K503: =IF(I503="","",MAX(0,I503-IF(J503="",0,J503)))

Sheet Productos
A1: Catálogo de productos · por completar
A2: Cuando me compartas los precios, aquí quedarán nombre, variante, unidad y precio para revisar.
A3: Producto | B3: Variante / código | C3: Unidad de cobro | D3: Precio de lista | E3: ¿Incluye IVA? | F3: Notas / medidas
A4: Borde ballena | B4: 50 x 40 cm | C4: unidad | D4: 5500 | E4: Sí | F4: Precio final por unidad, con impuestos incluidos. No sumar IVA. Fuente: imagen 1.
A5: Borde ballena nariz | B5: 50 x 50 cm | C5: unidad | D5: 6000 | E5: Sí | F5: Precio final por unidad, con impuestos incluidos. No sumar IVA. Fuente: imagen 1.
A6: Borde recto con nariz | B6: 50 x 50 cm | C6: unidad | D6: 6000 | E6: Sí | F6: Precio final por unidad. Foto recibida: 50 x 50 cm, espesor 3 cm, interior/exterior, antideslizante, atérmico y alta resistencia. Colores según ficha.
A7: Borde ballena curvo | B7: 23 x 40 cm | C7: unidad | D7: 4000 | E7: Sí | F7: Precio final por unidad, con impuestos incluidos. No sumar IVA. Fuente: imagen 1.
A8: Terraza | B8: 50 x 50 cm | C8: unidad | D8: 3800 | E8: Sí | F8: Precio final por unidad, con impuestos incluidos. No sumar IVA. Fuente: imagen 1.
A9: Pastelones | B9: 50 x 50 cm | C9: unidad | D9: 2600 | E9: Sí | F9: Precio final por unidad, con impuestos incluidos. No sumar IVA. Fuente: imagen 1.
A10: Pastelones | B10: 50 x 40 cm | C10: unidad | D10: 1600 | E10: Sí | F10: Precio final por unidad, con impuestos incluidos. No sumar IVA. Fuente: imagen 1.
A11: Ladrillo cruzado | B11: 40 x 40 cm | C11: unidad | D11: 1600 | E11: Sí | F11: Pastelón 40x40; 2 cm; interior/exterior; alta resistencia. Precio según regla indicada por Diego.
A12: Sol | B12: 40 x 40 cm | C12: unidad | D12: 1600 | E12: Sí | F12: Pastelón 40x40; 2 cm; interior/exterior; alta resistencia. Foto recibida.
A13: Adoquín | B13: 40 x 40 cm | C13: unidad | D13: 1600 | E13: Sí | F13: Pastelón 40x40; 2 cm; interior/exterior; alta resistencia. Foto recibida.
A14: Laja española | B14: 40 x 40 cm | C14: unidad | D14: 1600 | E14: Sí | F14: Pastelón 40x40; 2 cm; interior/exterior; alta resistencia. Foto recibida.
A15: Dormiente 1 | B15: 16 x 40 cm | E15: Por confirmar | F15: 3 cm; interior/exterior; antideslizante, atérmico, alta resistencia. Precio pendiente.
A16: Dormiente 2 | B16: 16 x 40 cm | E16: Por confirmar | F16: 3 cm; interior/exterior; antideslizante, atérmico, alta resistencia. Precio pendiente.
A17: Deck madera | B17: 50 x 50 cm | C17: unidad | D17: 4000 | E17: Sí | F17: 3 cm; interior/exterior; antideslizante, atérmico, alta resistencia. Precio corregido a $4.000 por unidad.
A18: Sol rústico | B18: 40 x 40 cm | C18: unidad | D18: 1600 | E18: Sí | F18: Pastelón 40x40, espesor 2 cm, interior/exterior y alta resistencia. Nombre inferido de la ficha parcialmente cubierta.
A19: Flor de lis | B19: 40 x 40 cm | C19: unidad | D19: 1600 | E19: Sí | F19: Pastelón 40x40, espesor 2 cm, interior/exterior y alta resistencia. Nombre inferido de la ficha parcialmente cubierta.
A20: Esquina piscina | B20: 50 x 50 cm | E20: Por confirmar | F20: Espesor 3 cm, interior/exterior, antideslizante, atérmico y alta resistencia. Precio pendiente.
A21: Extensión borde piscina | B21: 50 x 50 cm | E21: Por confirmar | F21: Espesor 3 cm, interior/exterior, antideslizante, atérmico y alta resistencia. Precio pendiente.

Sheet Resumen
A1: Resumen de ventas y comisiones
A3: Tasa de comisión | B3: 0.1
A5: Ventas cerradas | B5: =COUNTIF(Ventas!H4:H503,"Vendida")
A6: Productos vendidos (sin envío) | B6: =SUMIF(Ventas!H4:H503,"Vendida",Ventas!E4:E503)
A7: Envío cobrado | B7: =SUMIF(Ventas!H4:H503,"Vendida",Ventas!F4:F503)
A8: Total cobrado al cliente | B8: =SUMIF(Ventas!H4:H503,"Vendida",Ventas!G4:G503)
A9: Comisión generada | B9: =SUM(Ventas!I4:I503)
A10: Comisión pagada | B10: =SUM(Ventas!J4:J503)
A11: Comisión pendiente | B11: =SUM(Ventas!K4:K503)
A13: Base de comisión: solo productos cobrados, sin envío.

Sheet Referencias
A1: Datos visibles en las imágenes recibidas
A3: Imagen 1: tabla de 7 productos con precio por unidad.
A4: Imagen 2: tonos amarillado, blanco, rojo, crema, beige, gris y amarillo. Falta confirmar a qué productos aplican.
A5: Imágenes 3 y 4: Ladrillo cruzado 40 x 40 cm, espesor 2 cm. Se aplica la regla de pastelones 40x40 a $1.600 c/u.
A7: Los siete precios de la imagen 1 son finales, con todo incluido. El envío se registra por separado y no integra la comisión.
A8: Foto posterior: Borde recto con nariz 50 x 50 cm; asociado al precio de $6.000 por unidad de la imagen 1.
A9: Fotos nuevas: Sol, Adoquín y Laja española 40x40 a $1.600 c/u; Dormiente 1 y 2 sin precio; Deck madera 50x50 a $4.000 c/u.
A10: Cinco fotos adicionales: Ladrillo cruzado duplicado y más claro; Sol rústico y Flor de lis 40x40 a $1.600 c/u; Esquina piscina y Extensión borde piscina 50x50 sin precio.
