Workbook

Sheet Supuestos
A1: Supuestos (editar celdas azules)
A3: USD → CLP | B3: 978.55 | C3: Cierre 15-oct-2026, Infobae (no es el dólar observado oficial)
A4: UF → CLP | B4: 41162.73 | C4: 15-oct-2026, uf-hoy.com
A5: IVA | B5: 0.19 | C5: Tasa general Chile

Sheet Precios
A1: Producto | B1: Plan ZeroAI | C1: Precio ZeroAI neto (CLP/mes) | D1: Con IVA (CLP) | E1: Setup neto (CLP) | F1: Comparable más cercano | G1: Precio comparable (original) | H1: Moneda | I1: Comparable en CLP | J1: Diferencia vs comparable | K1: Fuente | L1: Confianza
A2: Leads B2B | B2: STARTER (50 leads) | C2: 69000 | D2: =C2*(1+Supuestos!$B$5) | E2: 0 | F2: AiSDR Self-serve, 50 personas (US$1,50 c/u) | G2: 75 | H2: USD | I2: =IF(H2="USD",G2*Supuestos!$B$3,IF(H2="UF",G2*Supuestos!$B$4,G2)) | J2: =IF(I2=0,"",C2/I2-1) | K2: aisdr.com/pricing, leído 15-oct-2026 | L2: Alta
A3: Leads B2B | B3: GROWTH (200 leads) | C3: 229000 | D3: =C3*(1+Supuestos!$B$5) | E3: 0 | F3: AiSDR Self-serve, 200 personas | G3: 300 | H3: USD | I3: =IF(H3="USD",G3*Supuestos!$B$3,IF(H3="UF",G3*Supuestos!$B$4,G3)) | J3: =IF(I3=0,"",C3/I3-1) | K3: aisdr.com/pricing, leído 15-oct-2026 | L3: Alta
A4: Leads B2B | B4: SCALE (500 leads) | C4: 449000 | D4: =C4*(1+Supuestos!$B$5) | E4: 0 | F4: Nexor Basic (500 leads propios, servicio completo) | G4: 500 | H4: USD | I4: =IF(H4="USD",G4*Supuestos!$B$3,IF(H4="UF",G4*Supuestos!$B$4,G4)) | J4: =IF(I4=0,"",C4/I4-1) | K4: HubSpot Marketplace, leído 15-oct-2026 | L4: Alta
A5: Agente WhatsApp | B5: Base (1.000 conv.) | C5: 119000 | D5: =C5*(1+Supuestos!$B$5) | E5: 250000 | F5: Leadsales Profesional (autoservicio) | G5: 133 | H5: USD | I5: =IF(H5="USD",G5*Supuestos!$B$3,IF(H5="UF",G5*Supuestos!$B$4,G5)) | J5: =IF(I5=0,"",C5/I5-1) | K5: leadsales.io/precios, leído 15-oct-2026 | L5: Alta
A6: Agente WhatsApp | B6: Base (1.000 conv.) | C6: 119000 | D6: =C6*(1+Supuestos!$B$5) | E6: 250000 | F6: Vozia / DuoTach (done-for-you) | G6: 200 | H6: USD | I6: =IF(H6="USD",G6*Supuestos!$B$3,IF(H6="UF",G6*Supuestos!$B$4,G6)) | J6: =IF(I6=0,"",C6/I6-1) | K6: duotach.com/chatbots | L6: Media
A7: Agente WhatsApp | B7: Base (1.000 conv.) | C7: 119000 | D7: =C7*(1+Supuestos!$B$5) | E7: 250000 | F7: N5 Go Starter IA | G7: 10 | H7: UF | I7: =IF(H7="USD",G7*Supuestos!$B$3,IF(H7="UF",G7*Supuestos!$B$4,G7)) | J7: =IF(I7=0,"",C7/I7-1) | K7: ia.n5go.cl, leído 15-oct-2026 | L7: Alta
A8: Automatización comercial | B8: Pack pyme | C8: 129000 | D8: =C8*(1+Supuestos!$B$5) | E8: 390000 | F8: Paquete básico pyme (guía) | G8: 150 | H8: USD | I8: =IF(H8="USD",G8*Supuestos!$B$3,IF(H8="UF",G8*Supuestos!$B$4,G8)) | J8: =IF(I8=0,"",C8/I8-1) | K8: ecosistemastartup.com, jul-2026 | L8: Baja
A9: Agentic marketing | B9: Fee de gestión | C9: 290000 | D9: =C9*(1+Supuestos!$B$5) | E9: 0 | F9: Agencia C (Labdeco), plan pequeño | G9: 8 | H9: UF | I9: =IF(H9="USD",G9*Supuestos!$B$3,IF(H9="UF",G9*Supuestos!$B$4,G9)) | J9: =IF(I9=0,"",C9/I9-1) | K9: labdeco.cl, 28-sep-2026 | L9: Media
A11: Meta WhatsApp Chile (tarifa oficial CLP, desde 1-oct-2026): marketing 78,49 · utilidad/autenticación/servicio 17,66 por mensaje. Se traspasa a costo, 0% de recargo.
A12: Negativo en 'Diferencia' = ZeroAI más barato. Celdas azules = supuestos editables. Precios neto + IVA. Fuente completa: 'Precios competencia Chile octubre 2026.md'.
